lib_ml/__init__.py
lib_ml/preprocessing.py
lib_ml_remla_12-0.1.10.dist-info/METADATA
lib_ml_remla_12-0.1.10.dist-info/WHEEL
lib_ml_remla_12-0.1.10.dist-info/top_level.txt
lib_ml_remla_12-0.1.10.dist-info/RECORD
